interfaz/__init__.py
interfaz/robotica.py
interfazrobotica/__init__.py
interfazrobotica/interfazrobotica.py
interfaz-0.2.0.dist-info/LICENSE
interfaz-0.2.0.dist-info/METADATA
interfaz-0.2.0.dist-info/WHEEL
interfaz-0.2.0.dist-info/top_level.txt
interfaz-0.2.0.dist-info/RECORD
